getindata_kedro_starters/__init__.py
getindata_kedro_starters/pyspark-iris-running-on-gcp-dataproc-serverless/.gitignore
getindata_kedro_starters/pyspark-iris-running-on-gcp-dataproc-serverless/ADJUSTMENTS.md
getindata_kedro_starters/pyspark-iris-running-on-gcp-dataproc-serverless/README.md
getindata_kedro_starters/pyspark-iris-running-on-gcp-dataproc-serverless/cookiecutter.json
getindata_kedro_starters/pyspark-iris-running-on-gcp-dataproc-serverless/credentials.yml
getindata_kedro_starters/pyspark-iris-running-on-gcp-dataproc-serverless/images/iris_pipeline.png
getindata_kedro_starters/pyspark-iris-running-on-gcp-dataproc-serverless/prompts.yml
getindata_kedro_starters/pyspark-iris-running-on-gcp-dataproc-serverless/{{ cookiecutter.repo_name }}/.dockerignore
getindata_kedro_starters/pyspark-iris-running-on-gcp-dataproc-serverless/{{ cookiecutter.repo_name }}/.gitignore
getindata_kedro_starters/pyspark-iris-running-on-gcp-dataproc-serverless/{{ cookiecutter.repo_name }}/Dockerfile
getindata_kedro_starters/pyspark-iris-running-on-gcp-dataproc-serverless/{{ cookiecutter.repo_name }}/README.md
getindata_kedro_starters/pyspark-iris-running-on-gcp-dataproc-serverless/{{ cookiecutter.repo_name }}/__init__.py
getindata_kedro_starters/pyspark-iris-running-on-gcp-dataproc-serverless/{{ cookiecutter.repo_name }}/conf/README.md
getindata_kedro_starters/pyspark-iris-running-on-gcp-dataproc-serverless/{{ cookiecutter.repo_name }}/conf/base/catalog.yml
getindata_kedro_starters/pyspark-iris-running-on-gcp-dataproc-serverless/{{ cookiecutter.repo_name }}/conf/base/logging.yml
getindata_kedro_starters/pyspark-iris-running-on-gcp-dataproc-serverless/{{ cookiecutter.repo_name }}/conf/base/parameters.yml
getindata_kedro_starters/pyspark-iris-running-on-gcp-dataproc-serverless/{{ cookiecutter.repo_name }}/conf/base/spark.yml
getindata_kedro_starters/pyspark-iris-running-on-gcp-dataproc-serverless/{{ cookiecutter.repo_name }}/conf/dataproc-serverless/catalog.yml
getindata_kedro_starters-0.2.0.dist-info/entry_points.txt
getindata_kedro_starters-0.2.0.dist-info/METADATA
getindata_kedro_starters-0.2.0.dist-info/LICENSE
getindata_kedro_starters-0.2.0.dist-info/WHEEL
getindata_kedro_starters-0.2.0.dist-info/RECORD
