Metadata-Version: 2.1
Name: getindata-kedro-starters
Version: 0.2.0
Summary: Starters for kedro projects to simplify pipelines deployment using GetInData plugins
Home-page: https://github.com/getindata/kedro-starters
License: Apache-2.0
Keywords: kedro,kedro starters,mlops
Author: Michał Bryś
Author-email: michal.brys@getindata.com
Requires-Python: >=3.8,<3.11
Classifier: Development Status :: 4 - Beta
Classifier: License :: OSI Approved :: Apache Software License
Classifier: Programming Language :: Python :: 3
Classifier: Programming Language :: Python :: 3.8
Classifier: Programming Language :: Python :: 3.9
Classifier: Programming Language :: Python :: 3.10
Project-URL: Documentation, https://getindata-kedro-starters.readthedocs.io/
Project-URL: Repository, https://github.com/getindata/kedro-starters
